bear_dereth/README.md
bear_dereth/__init__.py
bear_dereth/__main__.py
bear_dereth/async_stuffs.py
bear_dereth/dynamic_meth.py
bear_dereth/platform_utils.py
bear_dereth/py.typed
bear_dereth/sentinels.py
bear_dereth/system_bools.py
bear_dereth/_internal/__init__.py
bear_dereth/_internal/_info.py
bear_dereth/_internal/_version.py
bear_dereth/_internal/_version.pyi
bear_dereth/_internal/cli.py
bear_dereth/_internal/debug.py
bear_dereth/cli/__init__.py
bear_dereth/cli/arg_helpers.py
bear_dereth/cli/commands.py
bear_dereth/cli/exit_code.py
bear_dereth/cli/shells.py
bear_dereth/cli/typer_bridge.py
bear_dereth/cli/shell/__init__.py
bear_dereth/cli/shell/_base_command.py
bear_dereth/cli/shell/_base_shell.py
bear_dereth/codecs/__init__.py
bear_dereth/codecs/message_pack/README.md
bear_dereth/codecs/message_pack/__init__.py
bear_dereth/codecs/message_pack/_packing.py
bear_dereth/codecs/message_pack/_unpacking.py
bear_dereth/codecs/message_pack/msg_pack_handler.py
bear_dereth/codecs/message_pack/packing.py
bear_dereth/codecs/message_pack/unpacking.py
bear_dereth/codecs/message_pack/common/__init__.py
bear_dereth/codecs/message_pack/common/_fix_families.py
bear_dereth/codecs/message_pack/common/_msgpack_tag.py
bear_dereth/codecs/message_pack/common/exceptions.py
bear_dereth/codecs/toon/__init__.py
bear_dereth/codecs/toon/constants.py
bear_dereth/config/README.md
bear_dereth/config/__init__.py
bear_dereth/config/_base_settings.py
bear_dereth/config/config_manager.py
bear_dereth/config/dir_manager.py
bear_dereth/config/quick_settings.py
bear_dereth/config/settings_db_cls.py
bear_dereth/config/settings_manager.py
bear_dereth/config/settings_path.py
bear_dereth/constants/README.md
bear_dereth/constants/__init__.py
bear_dereth/constants/binary_types.py
bear_dereth/constants/exceptions.py
bear_dereth/constants/file_size.py
bear_dereth/constants/http_status_code.py
bear_dereth/data_structs/README.md
bear_dereth/data_structs/__init__.py
bear_dereth/data_structs/autosort_list.py
bear_dereth-0.4.6.dist-info/METADATA
bear_dereth-0.4.6.dist-info/WHEEL
bear_dereth-0.4.6.dist-info/entry_points.txt
bear_dereth-0.4.6.dist-info/RECORD
