Metadata-Version: 2.4
Name: bear-dereth
Version: 0.4.6
Summary: A set of common tools for various bear projects.
Author-email: chaz <bright.lid5647@fastmail.com>
Requires-Python: >=3.13
Requires-Dist: bear-epoch-time>=1.2.6
Requires-Dist: distro>=1.9.0
Requires-Dist: funcy-bear>=0.0.9
Requires-Dist: lazy-bear>=0.0.6
Requires-Dist: pydantic>=2.11.5
Requires-Dist: pyyaml>=6.0.3
Requires-Dist: rich>=14.1.0
Requires-Dist: singleton-base>=1.2.3
Requires-Dist: tomlkit>=0.13.3
